pass_gen/__init__.py
pass_gen/__main__.py
pass_gen/cli.py
pass_gen-0.0.5.dist-info/LICENSE
pass_gen-0.0.5.dist-info/METADATA
pass_gen-0.0.5.dist-info/WHEEL
pass_gen-0.0.5.dist-info/entry_points.txt
pass_gen-0.0.5.dist-info/top_level.txt
pass_gen-0.0.5.dist-info/RECORD
