Metadata-Version: 2.1
Name: pass-gen
Version: 0.0.5
Summary: Generate random password
Home-page: https://github.com/Aionmone/pass_gen
Author: Abdulrahman M. Zaky
Author-email: aionmone14@gmail.com
License: MIT
Project-URL: Bug Tracker, https://github.com/Aionmone/pass_gen/issues
Platform: UNKNOWN
Classifier: Programming Language :: Python :: 3
Classifier: Operating System :: OS Independent
Requires-Dist: click
